{
    "name": "Intercom API",
    "apiVersion": "3",
    "baseUrl": "https://api.intercom.io/",
    "description": "The Intercom API",
    "includes": [
        "intercom_public_company.json",
        "intercom_public_conversation.json",
        "intercom_public_count.json",
        "intercom_public_event.json",
        "intercom_public_tag.json",
        "intercom_public_note.json",
        "intercom_public_segment.json",
        "intercom_public_admin.json",
        "intercom_public_user.json",
        "intercom_public_contact.json",
        "intercom_public_job.json",
        "intercom_public_abstract_operations.json"
    ]
}
